webStreamViewer/__init__.py
webStreamViewer/webViewer.py
webStreamViewer/templates/home.html
webStreamViewer/templates/subpage.html
webStreamViewer-1.0.0.dist-info/METADATA
webStreamViewer-1.0.0.dist-info/WHEEL
webStreamViewer-1.0.0.dist-info/license.txt
webStreamViewer-1.0.0.dist-info/top_level.txt
webStreamViewer-1.0.0.dist-info/RECORD
