Metadata-Version: 2.1
Name: webStreamViewer
Version: 1.0.0
Summary: opencv-style image display that displays the image/stream on a local webserver instead of a screen.
Home-page: https://github.com/TzurSoffer/webVideoViewer/tree/main
Author: Tzur Soffer
Author-email: tzur.soffer@gmail.com
Classifier: Programming Language :: Python :: 3
Classifier: License :: OSI Approved :: MIT License
Classifier: Operating System :: OS Independent
Requires-Python: >=3.6
License-File: license.txt
Requires-Dist: numpy
Requires-Dist: simplejpeg
Requires-Dist: flask
